{
  "timestamp": "2026-01-14T18:36:04.955585",
  "converted_pdfs": [
    {
      "file": "gateoverflow_volume1.pdf",
      "md_path": "/home/myrrical/Miscellaneous/Coding-Cool/Projects/GATE Prep/quiz-app/data/imports/gateoverflow_volume1.md",
      "text_length": 804851,
      "images": 322
    },
    {
      "file": "gateoverflow_volume2.pdf",
      "md_path": "/home/myrrical/Miscellaneous/Coding-Cool/Projects/GATE Prep/quiz-app/data/imports/gateoverflow_volume2.md",
      "text_length": 1369005,
      "images": 424
    }
  ],
  "pages_total": 0,
  "candidates_found": 70,
  "duplicates_found": 4,
  "new_added": 65,
  "added_ids": [
    "Q00001",
    "Q00002",
    "Q00003",
    "Q00004",
    "Q00005",
    "Q00006",
    "Q00007",
    "Q00008",
    "Q00009",
    "Q00010",
    "Q00011",
    "Q00012",
    "Q00013",
    "Q00014",
    "Q00015",
    "Q00016",
    "Q00017",
    "Q00018",
    "Q00019",
    "Q00020",
    "Q00021",
    "Q00022",
    "Q00023",
    "Q00024",
    "Q00025",
    "Q00026",
    "Q00027",
    "Q00028",
    "Q00029",
    "Q00030",
    "Q00031",
    "Q00032",
    "Q00033",
    "Q00034",
    "Q00035",
    "Q00036",
    "Q00037",
    "Q00038",
    "Q00039",
    "Q00040",
    "Q00041",
    "Q00042",
    "Q00043",
    "Q00044",
    "Q00045",
    "Q00046",
    "Q00047",
    "Q00048",
    "Q00049",
    "Q00050",
    "Q00051",
    "Q00052",
    "Q00053",
    "Q00054",
    "Q00055",
    "Q00056",
    "Q00057",
    "Q00058",
    "Q00059",
    "Q00060",
    "Q00061",
    "Q00062",
    "Q00063",
    "Q00064",
    "Q00065"
  ],
  "flagged_for_review": [],
  "errors": []
}